nb2latex/__init__.py
nb2latex/nb2latex.py
nb2latex-0.1.4.dist-info/licenses/LICENSE
nb2latex-0.1.4.dist-info/METADATA
nb2latex-0.1.4.dist-info/WHEEL
nb2latex-0.1.4.dist-info/entry_points.txt
nb2latex-0.1.4.dist-info/top_level.txt
nb2latex-0.1.4.dist-info/RECORD
