Metadata-Version: 2.4
Name: nb2latex
Version: 0.1.4
Summary: CLI to convert Jupyter notebooks to a single LaTeX document
Author-email: Archie Benn <archiesnbenn@gmail.com>
License: MIT License
Requires-Python: >=3.12
License-File: LICENSE
Requires-Dist: nbconvert>=7.16.6
Requires-Dist: notebook
Requires-Dist: ipykernel
Dynamic: license-file
